damei/__init__.py
damei/version.py
damei/comm/__init__.py
damei/comm/ffmpeg/__init__.py
damei/comm/ffmpeg/ffmpeg.py
damei/controls/__init__.py
damei/controls/color.py
damei/data/__init__.py
damei/data/check_dataset.py
damei/data/augment/__init__.py
damei/data/augment/augment_dataset.py
damei/data/augment/dynamic_background.py
damei/data/augment/multiscale_slice.py
damei/dmsystem/__init__.py
damei/dmsystem/system.py
damei/functions/__init__.py
damei/functions/func.py
damei/functions/general.py
damei/functions/sub_process.py
damei/functions/torch_utils.py
damei/misc/__init__.py
damei/misc/discard_config_loader.py
damei/misc/dm_rsa.py
damei/misc/dmscp.py
damei/misc/fake_argparse.py
damei/misc/logger.py
damei/misc/misc_func.py
damei/misc/pyinstaller.py
damei/misc/run_frp.py
damei/misc/time.py
damei/misc/scrcpy/__init__.py
damei/misc/scrcpy/scrcpy.py
damei/nn/__init__.py
damei/nn/api/__init__.py
damei/nn/api/base.py
damei/nn/api/registry.py
damei/nn/api/utils.py
damei/nn/config/__init__.py
damei/nn/config/uaii_deepsort_config.py
damei/nn/config/uaii_seyolov5_config.py
damei/nn/config/uaii_stream_config.py
damei/nn/config/visible_loader_config.py
damei/nn/modules/__init__.py
damei/nn/modules/exporter/__init__.py
damei/nn/modules/exporter/vis_exporter/__init__.py
damei/nn/modules/loader/__init__.py
damei/nn/modules/loader/vis_loader/__init__.py
damei/nn/modules/loader/vis_loader/dataloader.py
damei/nn/modules/loader/vis_loader/datasets.py
damei/nn/modules/preset/__init__.py
damei/nn/modules/preset/io_input.py
damei/nn/modules/preset/io_output.py
damei/nn/test/__init__.py
damei/nn/test/test.py
damei/nn/test/test_module.py
damei/nn/uaii/__init__.py
damei/nn/uaii/uaii_main.py
damei/nn/uaii/datasets/__init__.py
damei/nn/uaii/datasets/dataloader.py
damei/nn/uaii/datasets/datasets.py
damei/nn/uaii/datasets/uaii_loaders.py
damei/nn/uaii/hub/__init__.py
damei/nn/uaii/hub/load_model.py
damei/nn/uaii/registry/__init__.py
damei/nn/uaii/registry/init_register.py
damei-1.1.135.dist-info/METADATA
damei-1.1.135.dist-info/WHEEL
damei-1.1.135.dist-info/top_level.txt
damei-1.1.135.dist-info/RECORD
