Metadata-Version: 2.1
Name: damei
Version: 1.1.135
Summary: Da Mei project with deep learning general functions.
Home-page: https://github.com/zhangzhengde0225/damei
Author: Zhengde Zhang
Author-email: drivener@163.com
License: MIT
Classifier: License :: OSI Approved :: MIT License
Classifier: Programming Language :: Python
Classifier: Programming Language :: Python :: 3
Classifier: Programming Language :: Python :: 3.6
Classifier: Programming Language :: Python :: Implementation :: CPython
Classifier: Programming Language :: Python :: Implementation :: PyPy
Requires-Python: >=3.6.0
Provides-Extra: rsa
Requires-Dist: rsa ; extra == 'rsa'
